nest_neat-1.0.dist-info/METADATA
nest_neat-1.0.dist-info/top_level.txt
nest_neat-1.0.dist-info/entry_points.txt
nest_neat-1.0.dist-info/WHEEL
nest_neat-1.0.dist-info/RECORD
nest_neat-1.0.dist-info/licenses/LICENSE.txt
neat/__version__.py
neat/__init__.py
neat/netsim.cpython-311-x86_64-linux-gnu.so
neat/factorydefaults.py
neat/modelreduction/cachetrees.py
neat/modelreduction/__init__.py
neat/modelreduction/compartmentfitter.py
neat/simulations/__init__.py
neat/simulations/nest/nestmodel.py
neat/simulations/nest/default_syns.nestml
neat/simulations/nest/__init__.py
neat/simulations/nest/nestml_tools.py
neat/simulations/net/Synapses.cc
neat/simulations/net/NETC.h
neat/simulations/net/netsim.cpp
neat/simulations/net/__init__.py
neat/simulations/net/Ionchannels.cc
neat/simulations/net/Tools.cc
neat/simulations/net/NETC.cc
neat/simulations/neuron/__init__.py
neat/simulations/neuron/neuronmodel.py
neat/simulations/neuron/mech_storage/double_exp_AMPA_NMDA_modified.mod
neat/simulations/neuron/mech_storage/double_exp_AMPA_NMDA.mod
neat/simulations/neuron/mech_storage/rel.mod
neat/simulations/neuron/mech_storage/epsc_double_exp.mod
neat/simulations/neuron/mech_storage/double_exp_AMPA_NMDA_rescaled.mod
neat/simulations/neuron/mech_storage/CaPump.mod
neat/simulations/neuron/mech_storage/conc_ca.mod
neat/simulations/neuron/mech_storage/CaDyn.mod
neat/simulations/neuron/mech_storage/VecStim.mod
neat/simulations/neuron/mech_storage/double_exp_AMPA_NMDA_rescaled_prox.mod
neat/simulations/neuron/mech_storage/SinClamp.mod
neat/simulations/neuron/mech_storage/OUReversal.mod
neat/simulations/neuron/mech_storage/double_exp_AMPA_NMDA_v_from_vector.mod
neat/simulations/neuron/mech_storage/exp_AMPA_NMDA.mod
neat/simulations/neuron/mech_storage/NMDA_Mg_T.mod
neat/simulations/neuron/mech_storage/gap.mod
neat/simulations/neuron/mech_storage/double_exp_AMPA_NMDA_modified2.mod
neat/simulations/neuron/mech_storage/release_BMK.mod
neat/simulations/neuron/mech_storage/OUClamp2.mod
neat/simulations/neuron/mech_storage/Shunt.mod
neat/simulations/neuron/mech_storage/WNClamp.mod
neat/simulations/neuron/mech_storage/OUClamp.mod
