Metadata-Version: 2.4
Name: nest-neat
Version: 1.0
Author: Willem Wybo, Jakob Jordan, Benjamin Ellenberger, Benjamin Torben-Nielsen
Maintainer-email: Willem Wybo <willem.a.m.wybo@gmail.com>
License: License
Project-URL: Documentation, https://neatdend.readthedocs.io/
Project-URL: Repository, https://github.com/unibe-cns/NEAT
Project-URL: Changelog, https://github.com/unibe-cns/NEAT/blob/master/changelog/v1.0.0.md
Classifier: Development Status :: 4 - Beta
Classifier: Programming Language :: Python :: 3
Requires-Python: >=3.9
License-File: LICENSE.txt
Requires-Dist: numpy>=1.24
Requires-Dist: matplotlib>=3.5.2
Requires-Dist: Cython>=3.0
Requires-Dist: scipy>=1.9.0
Requires-Dist: sympy>=1.10.1
Requires-Dist: pytest>=7.1.2
Requires-Dist: scikit_learn>=1.1.1
Requires-Dist: neuron>=8.2.0
Requires-Dist: dill>=0.3.8
Provides-Extra: docs
Requires-Dist: sphinx>=2.4.3; extra == "docs"
Requires-Dist: nbsphinx>=0.5.1; extra == "docs"
Requires-Dist: sphinx-gallery>=0.6.1; extra == "docs"
Requires-Dist: nb2plots>=0.6; extra == "docs"
Requires-Dist: pillow>=7.1.2; extra == "docs"
Requires-Dist: sphinx-material>=0.0.35; extra == "docs"
Requires-Dist: pillow>=7.1.2; extra == "docs"
Requires-Dist: numpy>=1.23.1; extra == "docs"
Requires-Dist: matplotlib>=3.5.2; extra == "docs"
Requires-Dist: scipy>=1.9.0; extra == "docs"
Requires-Dist: sympy>=1.10.1; extra == "docs"
Requires-Dist: pytest>=7.1.2; extra == "docs"
Requires-Dist: scikit_learn>=1.1.1; extra == "docs"
Requires-Dist: dill>=0.3.8; extra == "docs"
Dynamic: license-file
